matdata2py/__init__.py
matdata2py-0.1.1.dist-info/LICENSE
matdata2py-0.1.1.dist-info/METADATA
matdata2py-0.1.1.dist-info/WHEEL
matdata2py-0.1.1.dist-info/top_level.txt
matdata2py-0.1.1.dist-info/RECORD
