Metadata-Version: 2.1
Name: matdata2py
Version: 0.1.1
Summary: library to import Matlab data to python
Home-page: https://github.com/sammousavi/MatData2Py
Author: Sam Mousavi
Author-email: s.mo.mousavi@gmail.com
License: GNU
Classifier: Intended Audience :: Developers
Classifier: License :: OSI Approved :: GNU General Public License (GPL)
Classifier: Programming Language :: Python
Classifier: Programming Language :: Python :: 3
Classifier: Programming Language :: Python :: 3.6
Classifier: Programming Language :: Python :: 3.7
Classifier: Programming Language :: Python :: 3.8
Classifier: Programming Language :: Python :: 3.9
Classifier: Programming Language :: Python :: 3.10
Classifier: Programming Language :: Python :: 3.11
Classifier: Operating System :: OS Independent
License-File: LICENSE
Requires-Dist: numpy
Requires-Dist: h5py
